{
  "claim_boundary": "Forecast Phase 3 creates review-only negative-space watchlists. Missing, stale, or silent signal is not proof, prediction, alert, causal inference, autonomous action, or truth resolution.",
  "completed_at_utc": "2026-06-28T11:24:34.270009+00:00",
  "phase": "forecast_phase_3_negative_space_watchlist",
  "priority_counts": {
    "high": 1,
    "low": 7,
    "medium": 8
  },
  "records_artifact": "memory_layer/wiki/operator_memory/workstation_forecast_negative_space/forecast_phase3_negative_space_watchlist_records.jsonl",
  "status": "complete",
  "watch_type_counts": {
    "audit_review_or_hold": 1,
    "carried_forward_negative_space_candidate": 2,
    "claim_language_risk": 1,
    "math_overlay_available": 1,
    "pattern_concentration": 5,
    "secondary_condition_available": 1,
    "silent_expected_signal": 5
  },
  "watchlist_items_created": 16
}
